{
	"name": "obj",
	"plugin-id": "Sprite",
	"sid": 500839673660598,
	"instanceVariables": [
		{
			"name": "obj",
			"type": "string",
			"desc": "",
			"show": true,
			"sid": 177946799447380
		},
		{
			"name": "nick",
			"type": "string",
			"desc": "",
			"show": true,
			"sid": 112699643139686
		},
		{
			"name": "sX",
			"type": "number",
			"desc": "",
			"show": true,
			"sid": 397958724820332
		},
		{
			"name": "sY",
			"type": "number",
			"desc": "",
			"show": true,
			"sid": 610680298764209
		}
	],
	"behaviorTypes": [],
	"effectTypes": [],
	"members": [
		"ivBack"
	]
}