{
	"name": "roboTrash",
	"plugin-id": "Sprite",
	"sid": 407826414446178,
	"isGlobal": false,
	"editorNewInstanceIsReplica": true,
	"instanceVariables": [],
	"behaviorTypes": [],
	"effectTypes": [],
	"animations": {
		"items": [
			{
				"frames": [
					{
						"width": 192,
						"height": 202,
						"originX": 0.6302083333333334,
						"originY": 0.8910891089108911,
						"originalSource": "",
						"exportFormat": "lossless",
						"exportQuality": 0.8,
						"fileType": "image/png",
						"imageSpriteId": 2370890,
						"useCollisionPoly": true,
						"duration": 1,
						"tag": ""
					}
				],
				"sid": 961801131161964,
				"name": "Animation 1",
				"isLooping": false,
				"isPingPong": false,
				"repeatCount": 1,
				"repeatTo": 0,
				"speed": 12
			}
		],
		"subfolders": []
	}
}