{
	"name": "clouds",
	"plugin-id": "Sprite",
	"sid": 309322181433386,
	"instanceVariables": [
		{
			"name": "cloudName",
			"type": "string",
			"desc": "",
			"show": true,
			"sid": 815574693386191
		},
		{
			"name": "dontClose",
			"type": "boolean",
			"desc": "",
			"show": false,
			"sid": 875264206867601
		},
		{
			"name": "tweenOutTime",
			"type": "number",
			"desc": "",
			"show": false,
			"sid": 602817559504456
		},
		{
			"name": "istweenNow",
			"type": "boolean",
			"desc": "",
			"show": false,
			"sid": 345312138260445
		},
		{
			"name": "className",
			"type": "string",
			"desc": "",
			"show": false,
			"sid": 782772304263720
		},
		{
			"name": "filtred",
			"type": "boolean",
			"desc": "",
			"show": false,
			"sid": 901404071490554
		}
	],
	"behaviorTypes": [
		{
			"behaviorId": "MoveTo",
			"name": "MoveTo",
			"sid": 171996333140800
		}
	],
	"effectTypes": [],
	"members": [
		"dialogCloud"
	]
}