{
	"name": "_Sima",
	"events": [
		{
			"eventType": "comment",
			"text": "\n\n\n"
		},
		{
			"eventType": "block",
			"conditions": [
				{
					"id": "on-key-pressed",
					"objectClass": "Keyboard",
					"sid": 581483274762585,
					"parameters": {
						"key": 221
					}
				}
			],
			"actions": [
				{
					"customAction": "NoControl",
					"objectClass": "aIns",
					"sid": 713052204702464,
					"parameters": [
						true,
						true,
						"0"
					]
				}
			],
			"sid": 849285955273135,
			"disabled": true
		},
		{
			"eventType": "block",
			"conditions": [
				{
					"id": "on-key-pressed",
					"objectClass": "Keyboard",
					"sid": 670212514742023,
					"parameters": {
						"key": 71
					}
				}
			],
			"actions": [
				{
					"customAction": "act",
					"objectClass": "Bit",
					"sid": 722783494952307,
					"parameters": [
						false,
						"\"Nordik\"",
						"0",
						"\"zero\"",
						false,
						true,
						false,
						false,
						"0",
						"-1",
						"0"
					]
				}
			],
			"sid": 373233184601269
		},
		{
			"eventType": "block",
			"conditions": [
				{
					"id": "on-key-pressed",
					"objectClass": "Keyboard",
					"sid": 172012535943646,
					"parameters": {
						"key": 72
					}
				}
			],
			"actions": [
				{
					"customAction": "act",
					"objectClass": "Bit",
					"sid": 658184497244002,
					"parameters": [
						false,
						"\"zero\"",
						"0",
						"\"zero\"",
						false,
						false,
						false,
						true,
						"0",
						"-1",
						"0"
					]
				}
			],
			"sid": 155270061073967
		},
		{
			"eventType": "block",
			"conditions": [
				{
					"id": "on-key-pressed",
					"objectClass": "Keyboard",
					"sid": 697219478246413,
					"parameters": {
						"key": 74
					}
				}
			],
			"actions": [
				{
					"id": "set-animation",
					"objectClass": "Bit",
					"sid": 170330752645782,
					"parameters": {
						"animation": "\"angry\"",
						"from": "beginning"
					}
				}
			],
			"sid": 945219112751246
		},
		{
			"eventType": "block",
			"conditions": [
				{
					"id": "on-key-pressed",
					"objectClass": "Keyboard",
					"sid": 118670300815726,
					"parameters": {
						"key": 75
					}
				}
			],
			"actions": [
				{
					"id": "set-animation",
					"objectClass": "Bit",
					"sid": 725894088262380,
					"parameters": {
						"animation": "\"new\"",
						"from": "beginning"
					}
				}
			],
			"sid": 110665964044451
		},
		{
			"eventType": "block",
			"conditions": [
				{
					"id": "on-key-pressed",
					"objectClass": "Keyboard",
					"sid": 722695774086455,
					"parameters": {
						"key": 84
					}
				}
			],
			"actions": [
				{
					"id": "set-animation",
					"objectClass": "Bit",
					"sid": 558001852128354,
					"parameters": {
						"animation": "\"test\"",
						"from": "beginning"
					}
				}
			],
			"sid": 308262991323209
		},
		{
			"eventType": "comment",
			"text": ""
		},
		{
			"eventType": "block",
			"conditions": [
				{
					"id": "on-start-of-layout",
					"objectClass": "System",
					"sid": 262962021417101,
					"disabled": true
				},
				{
					"id": "on-key-pressed",
					"objectClass": "Keyboard",
					"sid": 855556713770204,
					"parameters": {
						"key": 68
					}
				}
			],
			"actions": [],
			"sid": 908578836354619,
			"children": [
				{
					"eventType": "block",
					"conditions": [
						{
							"id": "is-boolean-instance-variable-set",
							"objectClass": "persAdd",
							"sid": 782874030831242,
							"parameters": {
								"instance-variable": "active"
							}
						}
					],
					"actions": [
						{
							"customAction": "on",
							"objectClass": "persAdd",
							"sid": 559406877813731
						}
					],
					"sid": 936944638984678
				}
			],
			"isOrBlock": true
		},
		{
			"eventType": "comment",
			"text": ""
		},
		{
			"aceType": "action",
			"aceName": "on",
			"objectClass": "persAdd",
			"functionDescription": "",
			"functionCategory": "",
			"functionReturnType": "none",
			"functionCopyPicked": false,
			"functionIsAsync": false,
			"functionParameters": [],
			"eventType": "custom-ace-block",
			"conditions": [],
			"actions": [],
			"sid": 913421933344442,
			"children": [
				{
					"eventType": "block",
					"conditions": [
						{
							"id": "is-boolean-instance-variable-set",
							"objectClass": "persAdd",
							"sid": 444667983620939,
							"parameters": {
								"instance-variable": "on"
							},
							"isInverted": true
						}
					],
					"actions": [],
					"sid": 504803622592328,
					"children": [
						{
							"eventType": "block",
							"conditions": [
								{
									"id": "is-boolean-instance-variable-set",
									"objectClass": "persAdd",
									"sid": 581439564224011,
									"parameters": {
										"instance-variable": "Bit"
									}
								}
							],
							"actions": [
								{
									"id": "set-position-to-another-object",
									"objectClass": "persAdd",
									"sid": 648456195424835,
									"parameters": {
										"object": "Bit",
										"image-point-optional": "persAdd.imPoint=\"zero\"?0:persAdd.imPoint"
									}
								},
								{
									"id": "set-scale",
									"objectClass": "persAdd",
									"sid": 318234364316574,
									"parameters": {
										"scale": "Self.scale*Bit.basisFullScale"
									}
								},
								{
									"id": "set-animation",
									"objectClass": "persAdd",
									"sid": 416174495789348,
									"parameters": {
										"animation": "Self.anim",
										"from": "beginning"
									}
								},
								{
									"id": "set-boolean-instvar",
									"objectClass": "persAdd",
									"sid": 659172359263742,
									"parameters": {
										"instance-variable": "on",
										"value": "true"
									}
								}
							],
							"sid": 555457346863733,
							"children": [
								{
									"eventType": "block",
									"conditions": [
										{
											"id": "compare-instance-variable",
											"objectClass": "persAdd",
											"sid": 610095198730433,
											"parameters": {
												"instance-variable": "imPoint",
												"comparison": 1,
												"value": "\"dialog\""
											}
										}
									],
									"actions": [
										{
											"id": "pin-to-object-properties",
											"objectClass": "persAdd",
											"sid": 446140766700131,
											"behaviorType": "Pin",
											"parameters": {
												"pin-to": "Bit",
												"x": true,
												"y": true,
												"angle": false,
												"width-type": "no",
												"height-type": "no",
												"z": false
											}
										}
									],
									"sid": 599814865860024
								}
							]
						}
					]
				},
				{
					"eventType": "block",
					"conditions": [
						{
							"id": "else",
							"objectClass": "System",
							"sid": 448585910799512
						},
						{
							"id": "is-boolean-instance-variable-set",
							"objectClass": "persAdd",
							"sid": 703922403627914,
							"parameters": {
								"instance-variable": "on"
							}
						}
					],
					"actions": [
						{
							"id": "unpin",
							"objectClass": "persAdd",
							"sid": 970029326163707,
							"behaviorType": "Pin"
						},
						{
							"id": "set-position",
							"objectClass": "persAdd",
							"sid": 286016969360178,
							"parameters": {
								"x": "-5955",
								"y": "-5955"
							}
						}
					],
					"sid": 401895391920359
				}
			]
		},
		{
			"eventType": "block",
			"conditions": [
				{
					"id": "on-animation-finished",
					"objectClass": "persAdd",
					"sid": 858699991129277,
					"parameters": {
						"animation": "\"on\""
					}
				}
			],
			"actions": [
				{
					"id": "set-animation",
					"objectClass": "persAdd",
					"sid": 270218567831068,
					"parameters": {
						"animation": "\"idle\"",
						"from": "beginning"
					}
				}
			],
			"sid": 788939384013765
		},
		{
			"eventType": "comment",
			"text": ""
		},
		{
			"eventType": "block",
			"conditions": [
				{
					"id": "on-drag-start",
					"objectClass": "persAdd",
					"sid": 402800456277170,
					"behaviorType": "DragDrop"
				}
			],
			"actions": [
				{
					"id": "set-boolean-instvar",
					"objectClass": "persAdd",
					"sid": 829690715164702,
					"parameters": {
						"instance-variable": "active",
						"value": "false"
					}
				},
				{
					"id": "unpin",
					"objectClass": "persAdd",
					"sid": 857657395762488,
					"behaviorType": "Pin"
				}
			],
			"sid": 171135312770810
		},
		{
			"eventType": "comment",
			"text": ""
		},
		{
			"eventType": "block",
			"conditions": [
				{
					"id": "on-drop",
					"objectClass": "persAdd",
					"sid": 223399576198019,
					"behaviorType": "DragDrop"
				}
			],
			"actions": [],
			"sid": 997553122784250,
			"children": [
				{
					"eventType": "block",
					"conditions": [
						{
							"id": "is-boolean-instance-variable-set",
							"objectClass": "persAdd",
							"sid": 817806908857578,
							"parameters": {
								"instance-variable": "Bit"
							}
						}
					],
					"actions": [],
					"sid": 536530662431001,
					"children": [
						{
							"eventType": "block",
							"conditions": [
								{
									"id": "is-overlapping-another-object",
									"objectClass": "persAdd",
									"sid": 362552195658817,
									"parameters": {
										"object": "Bit"
									}
								}
							],
							"actions": [
								{
									"id": "set-boolean-instvar",
									"objectClass": "persAdd",
									"sid": 101511065880675,
									"parameters": {
										"instance-variable": "active",
										"value": "true"
									}
								},
								{
									"customAction": "on",
									"objectClass": "persAdd",
									"sid": 285073151188155
								}
							],
							"sid": 652061326376157
						},
						{
							"eventType": "block",
							"conditions": [
								{
									"id": "else",
									"objectClass": "System",
									"sid": 161849293801107
								}
							],
							"actions": [
								{
									"id": "set-y",
									"objectClass": "persAdd",
									"sid": 543898034416670,
									"parameters": {
										"y": "Self.Y+20"
									}
								},
								{
									"id": "set-scale",
									"objectClass": "persAdd",
									"sid": 115695936849580,
									"parameters": {
										"scale": "Self.scale*Bit.basisFullScale*1.5"
									}
								}
							],
							"sid": 750352705349600
						}
					]
				}
			]
		},
		{
			"eventType": "comment",
			"text": ""
		},
		{
			"eventType": "block",
			"conditions": [
				{
					"id": "is-boolean-instance-variable-set",
					"objectClass": "persAdd",
					"sid": 343376314782591,
					"parameters": {
						"instance-variable": "on"
					}
				},
				{
					"id": "is-overlapping-another-object",
					"objectClass": "persAdd",
					"sid": 249969433323611,
					"parameters": {
						"object": "cursor"
					},
					"isInverted": true
				},
				{
					"id": "compare-instance-variable",
					"objectClass": "camera",
					"sid": 212328615326766,
					"parameters": {
						"instance-variable": "index",
						"comparison": 0,
						"value": "aTools.n"
					}
				}
			],
			"actions": [],
			"sid": 260234794817743,
			"children": [
				{
					"eventType": "block",
					"conditions": [
						{
							"id": "is-boolean-instance-variable-set",
							"objectClass": "persAdd",
							"sid": 970910020717495,
							"parameters": {
								"instance-variable": "Bit"
							}
						}
					],
					"actions": [],
					"sid": 603873098566905,
					"children": [
						{
							"eventType": "block",
							"conditions": [
								{
									"id": "is-boolean-instance-variable-set",
									"objectClass": "persAdd",
									"sid": 177078064208376,
									"parameters": {
										"instance-variable": "over"
									}
								}
							],
							"actions": [
								{
									"id": "move-to-object",
									"objectClass": "persAdd",
									"sid": 625963726976469,
									"parameters": {
										"where": "in-front",
										"object": "Bit"
									}
								}
							],
							"sid": 384595205921005
						},
						{
							"eventType": "block",
							"conditions": [
								{
									"id": "is-boolean-instance-variable-set",
									"objectClass": "persAdd",
									"sid": 976300043448319,
									"parameters": {
										"instance-variable": "under"
									}
								}
							],
							"actions": [
								{
									"id": "move-to-object",
									"objectClass": "persAdd",
									"sid": 975782124473376,
									"parameters": {
										"where": "behind",
										"object": "Bit"
									}
								}
							],
							"sid": 986065984992109
						},
						{
							"eventType": "block",
							"conditions": [
								{
									"id": "is-boolean-instance-variable-set",
									"objectClass": "camera",
									"sid": 521789815594548,
									"parameters": {
										"instance-variable": "perspective"
									}
								}
							],
							"actions": [
								{
									"id": "set-scale",
									"objectClass": "persAdd",
									"sid": 303122296030083,
									"parameters": {
										"scale": "Self.scale*Bit.basisFullScale"
									}
								}
							],
							"sid": 261639202597970
						}
					]
				},
				{
					"eventType": "block",
					"conditions": [
						{
							"id": "compare-instance-variable",
							"objectClass": "persAdd",
							"sid": 545154841384197,
							"parameters": {
								"instance-variable": "imPoint",
								"comparison": 0,
								"value": "\"dialog\""
							}
						}
					],
					"actions": [
						{
							"id": "set-position-to-another-object",
							"objectClass": "persAdd",
							"sid": 312192150687318,
							"parameters": {
								"object": "Bit",
								"image-point-optional": "\"dialog\""
							}
						}
					],
					"sid": 865910010027460
				}
			]
		},
		{
			"eventType": "comment",
			"text": "",
			"background-color": [
				0.9019607843137255,
				0.9019607843137255,
				0.9019607843137255,
				1
			]
		},
		{
			"eventType": "block",
			"conditions": [
				{
					"id": "on-object-clicked",
					"objectClass": "Mouse",
					"sid": 876728622840671,
					"parameters": {
						"mouse-button": "right",
						"click-type": "clicked",
						"object-clicked": "persAdd"
					}
				}
			],
			"actions": [],
			"sid": 713392819968888,
			"disabled": true
		},
		{
			"eventType": "block",
			"conditions": [
				{
					"id": "on-key-pressed",
					"objectClass": "Keyboard",
					"sid": 761095046181047,
					"parameters": {
						"key": 68
					}
				}
			],
			"actions": [],
			"sid": 475941038681311,
			"disabled": true,
			"children": [
				{
					"eventType": "block",
					"conditions": [
						{
							"id": "is-boolean-instance-variable-set",
							"objectClass": "persAdd",
							"sid": 264001438086227,
							"parameters": {
								"instance-variable": "on"
							}
						}
					],
					"actions": [],
					"sid": 882138625912200,
					"disabled": true,
					"children": [
						{
							"eventType": "block",
							"conditions": [
								{
									"id": "is-boolean-instance-variable-set",
									"objectClass": "persAdd",
									"sid": 927082317392556,
									"parameters": {
										"instance-variable": "Bit"
									}
								}
							],
							"actions": [
								{
									"id": "set-position-to-another-object",
									"objectClass": "persAdd",
									"sid": 417610892769765,
									"parameters": {
										"object": "Bit",
										"image-point-optional": "persAdd.imPoint=\"zero\"?0:persAdd.imPoint"
									}
								},
								{
									"id": "pin-to-object-properties",
									"objectClass": "persAdd",
									"sid": 950357459282742,
									"behaviorType": "Pin",
									"parameters": {
										"pin-to": "Bit",
										"x": true,
										"y": true,
										"angle": false,
										"width-type": "no",
										"height-type": "no",
										"z": false
									}
								}
							],
							"sid": 557933806174344,
							"disabled": true
						}
					]
				},
				{
					"eventType": "block",
					"conditions": [
						{
							"id": "else",
							"objectClass": "System",
							"sid": 532238399006707
						},
						{
							"id": "is-boolean-instance-variable-set",
							"objectClass": "persAdd",
							"sid": 298467207545114,
							"parameters": {
								"instance-variable": "on"
							},
							"isInverted": true
						}
					],
					"actions": [
						{
							"id": "unpin",
							"objectClass": "persAdd",
							"sid": 446906344966084,
							"behaviorType": "Pin"
						},
						{
							"id": "set-position",
							"objectClass": "persAdd",
							"sid": 394560386345196,
							"parameters": {
								"x": "-5955",
								"y": "-5955"
							}
						}
					],
					"sid": 612682310337088,
					"disabled": true
				}
			]
		}
	],
	"sid": 400101348474627
}