{
	"name": "invSecR",
	"plugin-id": "Sprite",
	"sid": 899835348753590,
	"isGlobal": false,
	"editorNewInstanceIsReplica": true,
	"instanceVariables": [],
	"behaviorTypes": [],
	"effectTypes": [],
	"animations": {
		"items": [
			{
				"frames": [
					{
						"width": 135,
						"height": 138,
						"originX": 0.07407407407407407,
						"originY": 0.007246376811594203,
						"originalSource": "",
						"exportFormat": "lossless",
						"exportQuality": 0.8,
						"fileType": "image/png",
						"imageSpriteId": 1183102,
						"collisionPoly": {
							"points": [
								0.5611111111111111,
								0.22463768115942015,
								0.26851851851851843,
								0,
								0.9351851851851848,
								0,
								0.9296296296296291,
								0.7880434782608695,
								0.5518518518518516,
								0.9673913043478266,
								0.33518518518518525,
								0.9057971014492756,
								0.6148148148148146,
								0.5443840579710141
							]
						},
						"useCollisionPoly": true,
						"duration": 1,
						"tag": ""
					}
				],
				"sid": 719695873780559,
				"name": "Animation 1",
				"isLooping": false,
				"isPingPong": false,
				"repeatCount": 1,
				"repeatTo": 0,
				"speed": 0
			}
		],
		"subfolders": []
	}
}