{
	"name": "plantCBoomM",
	"plugin-id": "Sprite",
	"sid": 680137083503461,
	"isGlobal": false,
	"editorNewInstanceIsReplica": true,
	"instanceVariables": [
		{
			"name": "ind",
			"type": "number",
			"desc": "",
			"show": false,
			"sid": 959296140154451
		}
	],
	"behaviorTypes": [],
	"effectTypes": [],
	"animations": {
		"items": [
			{
				"frames": [
					{
						"width": 330,
						"height": 383,
						"originX": 0.48787878787878786,
						"originY": 0.9608355091383812,
						"originalSource": "",
						"exportFormat": "lossless",
						"exportQuality": 0.8,
						"fileType": "image/png",
						"imageSpriteId": 4456983,
						"useCollisionPoly": true,
						"imagePoints": [
							{
								"name": "Image Point 1",
								"x": 0.12727272727272726,
								"y": 0.4386422976501306
							},
							{
								"name": "Image Point 2",
								"x": 0.8212121212121212,
								"y": 0.360313315926893
							},
							{
								"name": "Image Point 3",
								"x": 0.20303030303030303,
								"y": 0.7989556135770235
							},
							{
								"name": "Image Point 4",
								"x": 0.8727272727272727,
								"y": 0.608355091383812
							}
						],
						"duration": 1,
						"tag": ""
					}
				],
				"sid": 640424071747677,
				"name": "Animation 1",
				"isLooping": false,
				"isPingPong": false,
				"repeatCount": 1,
				"repeatTo": 0,
				"speed": 12
			}
		],
		"subfolders": []
	}
}