{
	"name": "pagurus",
	"plugin-id": "Sprite",
	"sid": 851712595854448,
	"isGlobal": false,
	"editorNewInstanceIsReplica": true,
	"instanceVariables": [],
	"behaviorTypes": [],
	"effectTypes": [],
	"animations": {
		"items": [
			{
				"frames": [
					{
						"width": 10,
						"height": 10,
						"originX": 0.45217391304347826,
						"originY": 0.5,
						"originalSource": "",
						"exportFormat": "lossless",
						"exportQuality": 0.8,
						"fileType": "image/png",
						"imageSpriteId": 7541148,
						"useCollisionPoly": true,
						"duration": 1,
						"tag": ""
					}
				],
				"sid": 140877710901772,
				"name": "out",
				"isLooping": false,
				"isPingPong": false,
				"repeatCount": 1,
				"repeatTo": 0,
				"speed": 8
			},
			{
				"frames": [
					{
						"width": 22,
						"height": 22,
						"originX": 0.5,
						"originY": 0.5,
						"originalSource": "",
						"exportFormat": "lossless",
						"exportQuality": 0.8,
						"fileType": "image/png",
						"imageSpriteId": 2872999,
						"collisionPoly": {
							"points": [
								1,
								1,
								1,
								1,
								1,
								1
							]
						},
						"useCollisionPoly": true,
						"duration": 1,
						"tag": ""
					}
				],
				"sid": 937190703999855,
				"name": "zero",
				"isLooping": false,
				"isPingPong": false,
				"repeatCount": 1,
				"repeatTo": 0,
				"speed": 12
			},
			{
				"frames": [
					{
						"width": 395,
						"height": 554,
						"originX": 0.5594936708860759,
						"originY": 0.4729241877256318,
						"originalSource": "",
						"exportFormat": "lossless",
						"exportQuality": 0.8,
						"fileType": "image/png",
						"imageSpriteId": 3286602,
						"useCollisionPoly": true,
						"duration": 1,
						"tag": ""
					},
					{
						"width": 395,
						"height": 554,
						"originX": 0.5594936708860759,
						"originY": 0.4729241877256318,
						"originalSource": "",
						"exportFormat": "lossless",
						"exportQuality": 0.8,
						"fileType": "image/png",
						"imageSpriteId": 8066461,
						"useCollisionPoly": true,
						"duration": 1,
						"tag": ""
					},
					{
						"width": 395,
						"height": 554,
						"originX": 0.5594936708860759,
						"originY": 0.4729241877256318,
						"originalSource": "",
						"exportFormat": "lossless",
						"exportQuality": 0.8,
						"fileType": "image/png",
						"imageSpriteId": 7451671,
						"useCollisionPoly": true,
						"duration": 1,
						"tag": ""
					},
					{
						"width": 404,
						"height": 554,
						"originX": 0.5470297029702971,
						"originY": 0.4729241877256318,
						"originalSource": "",
						"exportFormat": "lossless",
						"exportQuality": 0.8,
						"fileType": "image/png",
						"imageSpriteId": 5657862,
						"useCollisionPoly": true,
						"duration": 1,
						"tag": ""
					},
					{
						"width": 470,
						"height": 554,
						"originX": 0.4702127659574468,
						"originY": 0.4729241877256318,
						"originalSource": "",
						"exportFormat": "lossless",
						"exportQuality": 0.8,
						"fileType": "image/png",
						"imageSpriteId": 4326812,
						"useCollisionPoly": true,
						"duration": 1,
						"tag": ""
					},
					{
						"width": 478,
						"height": 554,
						"originX": 0.46234309623430964,
						"originY": 0.4729241877256318,
						"originalSource": "",
						"exportFormat": "lossless",
						"exportQuality": 0.8,
						"fileType": "image/png",
						"imageSpriteId": 9156037,
						"useCollisionPoly": true,
						"duration": 1,
						"tag": ""
					},
					{
						"width": 500,
						"height": 554,
						"originX": 0.442,
						"originY": 0.4729241877256318,
						"originalSource": "",
						"exportFormat": "lossless",
						"exportQuality": 0.8,
						"fileType": "image/png",
						"imageSpriteId": 5157097,
						"useCollisionPoly": true,
						"duration": 1,
						"tag": ""
					},
					{
						"width": 500,
						"height": 554,
						"originX": 0.442,
						"originY": 0.4729241877256318,
						"originalSource": "",
						"exportFormat": "lossless",
						"exportQuality": 0.8,
						"fileType": "image/png",
						"imageSpriteId": 3166643,
						"useCollisionPoly": true,
						"duration": 1,
						"tag": ""
					},
					{
						"width": 498,
						"height": 554,
						"originX": 0.44377510040160645,
						"originY": 0.4729241877256318,
						"originalSource": "",
						"exportFormat": "lossless",
						"exportQuality": 0.8,
						"fileType": "image/png",
						"imageSpriteId": 9260562,
						"useCollisionPoly": true,
						"duration": 1,
						"tag": ""
					},
					{
						"width": 498,
						"height": 554,
						"originX": 0.44377510040160645,
						"originY": 0.4729241877256318,
						"originalSource": "",
						"exportFormat": "lossless",
						"exportQuality": 0.8,
						"fileType": "image/png",
						"imageSpriteId": 7055686,
						"useCollisionPoly": true,
						"duration": 1,
						"tag": "quest"
					},
					{
						"width": 498,
						"height": 601,
						"originX": 0.44377510040160645,
						"originY": 0.5141430948419301,
						"originalSource": "",
						"exportFormat": "lossless",
						"exportQuality": 0.8,
						"fileType": "image/png",
						"imageSpriteId": 5188399,
						"useCollisionPoly": true,
						"duration": 1,
						"tag": ""
					},
					{
						"width": 498,
						"height": 591,
						"originX": 0.44377510040160645,
						"originY": 0.505922165820643,
						"originalSource": "",
						"exportFormat": "lossless",
						"exportQuality": 0.8,
						"fileType": "image/png",
						"imageSpriteId": 382211,
						"useCollisionPoly": true,
						"duration": 1,
						"tag": ""
					},
					{
						"width": 498,
						"height": 580,
						"originX": 0.44377510040160645,
						"originY": 0.496551724137931,
						"originalSource": "",
						"exportFormat": "lossless",
						"exportQuality": 0.8,
						"fileType": "image/png",
						"imageSpriteId": 2680444,
						"useCollisionPoly": true,
						"duration": 5,
						"tag": ""
					},
					{
						"width": 500,
						"height": 554,
						"originX": 0.442,
						"originY": 0.4729241877256318,
						"originalSource": "",
						"exportFormat": "lossless",
						"exportQuality": 0.8,
						"fileType": "image/png",
						"imageSpriteId": 9584058,
						"useCollisionPoly": true,
						"duration": 1,
						"tag": "out"
					},
					{
						"width": 503,
						"height": 561,
						"originX": 0.4393638170974155,
						"originY": 0.47950089126559714,
						"originalSource": "",
						"exportFormat": "lossless",
						"exportQuality": 0.8,
						"fileType": "image/png",
						"imageSpriteId": 1107591,
						"useCollisionPoly": true,
						"duration": 1,
						"tag": ""
					},
					{
						"width": 442,
						"height": 555,
						"originX": 0.497737556561086,
						"originY": 0.4720720720720721,
						"originalSource": "",
						"exportFormat": "lossless",
						"exportQuality": 0.8,
						"fileType": "image/png",
						"imageSpriteId": 3822047,
						"useCollisionPoly": true,
						"duration": 1,
						"tag": ""
					},
					{
						"width": 471,
						"height": 606,
						"originX": 0.5371549893842887,
						"originY": 0.466996699669967,
						"originalSource": "",
						"exportFormat": "lossless",
						"exportQuality": 0.8,
						"fileType": "image/png",
						"imageSpriteId": 6046028,
						"useCollisionPoly": true,
						"duration": 1,
						"tag": ""
					},
					{
						"width": 631,
						"height": 464,
						"originX": 0.4041204437400951,
						"originY": 0.5150862068965517,
						"originalSource": "",
						"exportFormat": "lossless",
						"exportQuality": 0.8,
						"fileType": "image/png",
						"imageSpriteId": 1193753,
						"useCollisionPoly": true,
						"duration": 1,
						"tag": ""
					},
					{
						"width": 737,
						"height": 474,
						"originX": 0.4735413839891452,
						"originY": 0.510548523206751,
						"originalSource": "",
						"exportFormat": "lossless",
						"exportQuality": 0.8,
						"fileType": "image/png",
						"imageSpriteId": 6732844,
						"useCollisionPoly": true,
						"duration": 1,
						"tag": ""
					},
					{
						"width": 743,
						"height": 482,
						"originX": 0.4535666218034993,
						"originY": 0.5373443983402489,
						"originalSource": "",
						"exportFormat": "lossless",
						"exportQuality": 0.8,
						"fileType": "image/png",
						"imageSpriteId": 2609149,
						"useCollisionPoly": true,
						"duration": 1,
						"tag": ""
					},
					{
						"width": 828,
						"height": 416,
						"originX": 0.4855072463768116,
						"originY": 0.46634615384615385,
						"originalSource": "",
						"exportFormat": "lossless",
						"exportQuality": 0.8,
						"fileType": "image/png",
						"imageSpriteId": 6830541,
						"useCollisionPoly": true,
						"duration": 1,
						"tag": ""
					},
					{
						"width": 820,
						"height": 377,
						"originX": 0.44390243902439025,
						"originY": 0.5570291777188329,
						"originalSource": "",
						"exportFormat": "lossless",
						"exportQuality": 0.8,
						"fileType": "image/png",
						"imageSpriteId": 8406284,
						"useCollisionPoly": true,
						"duration": 1,
						"tag": ""
					},
					{
						"width": 885,
						"height": 287,
						"originX": 0.4858757062146893,
						"originY": 0.5121951219512195,
						"originalSource": "",
						"exportFormat": "lossless",
						"exportQuality": 0.8,
						"fileType": "image/png",
						"imageSpriteId": 5899525,
						"useCollisionPoly": true,
						"duration": 1,
						"tag": ""
					},
					{
						"width": 986,
						"height": 227,
						"originX": 0.5365111561866126,
						"originY": 0.6123348017621145,
						"originalSource": "",
						"exportFormat": "lossless",
						"exportQuality": 0.8,
						"fileType": "image/png",
						"imageSpriteId": 8042252,
						"useCollisionPoly": true,
						"duration": 1,
						"tag": ""
					},
					{
						"width": 222,
						"height": 173,
						"originX": 2.5495495495495497,
						"originY": 0.8034682080924855,
						"originalSource": "",
						"exportFormat": "lossless",
						"exportQuality": 0.8,
						"fileType": "image/png",
						"imageSpriteId": 9969609,
						"useCollisionPoly": true,
						"duration": 1,
						"tag": ""
					},
					{
						"width": 230,
						"height": 187,
						"originX": 2.882608695652174,
						"originY": 1.1443850267379678,
						"originalSource": "",
						"exportFormat": "lossless",
						"exportQuality": 0.8,
						"fileType": "image/png",
						"imageSpriteId": 4302232,
						"useCollisionPoly": true,
						"duration": 1,
						"tag": ""
					},
					{
						"width": 175,
						"height": 193,
						"originX": 3.834285714285714,
						"originY": 1.3730569948186528,
						"originalSource": "",
						"exportFormat": "lossless",
						"exportQuality": 0.8,
						"fileType": "image/png",
						"imageSpriteId": 1614776,
						"useCollisionPoly": true,
						"duration": 1,
						"tag": ""
					},
					{
						"width": 169,
						"height": 121,
						"originX": 3.5798816568047336,
						"originY": 2.603305785123967,
						"originalSource": "",
						"exportFormat": "lossless",
						"exportQuality": 0.8,
						"fileType": "image/png",
						"imageSpriteId": 4604619,
						"useCollisionPoly": true,
						"duration": 1,
						"tag": ""
					},
					{
						"width": 160,
						"height": 191,
						"originX": 3.2,
						"originY": 1.5654450261780104,
						"originalSource": "",
						"exportFormat": "lossless",
						"exportQuality": 0.8,
						"fileType": "image/png",
						"imageSpriteId": 9812585,
						"useCollisionPoly": true,
						"duration": 1,
						"tag": ""
					},
					{
						"width": 129,
						"height": 153,
						"originX": 4.1395348837209305,
						"originY": 1.477124183006536,
						"originalSource": "",
						"exportFormat": "lossless",
						"exportQuality": 0.8,
						"fileType": "image/png",
						"imageSpriteId": 2992567,
						"useCollisionPoly": true,
						"duration": 1,
						"tag": ""
					},
					{
						"width": 140,
						"height": 117,
						"originX": 4.621428571428571,
						"originY": 1.7863247863247864,
						"originalSource": "",
						"exportFormat": "lossless",
						"exportQuality": 0.8,
						"fileType": "image/png",
						"imageSpriteId": 7363634,
						"useCollisionPoly": true,
						"duration": 1,
						"tag": ""
					},
					{
						"width": 180,
						"height": 206,
						"originX": 4.355555555555555,
						"originY": 1.6699029126213591,
						"originalSource": "",
						"exportFormat": "lossless",
						"exportQuality": 0.8,
						"fileType": "image/png",
						"imageSpriteId": 17435,
						"useCollisionPoly": true,
						"duration": 1,
						"tag": ""
					},
					{
						"width": 82,
						"height": 193,
						"originX": 9.536585365853659,
						"originY": 2.2538860103626943,
						"originalSource": "",
						"exportFormat": "lossless",
						"exportQuality": 0.8,
						"fileType": "image/png",
						"imageSpriteId": 5364458,
						"useCollisionPoly": true,
						"duration": 1,
						"tag": ""
					},
					{
						"width": 45,
						"height": 103,
						"originX": 17.022222222222222,
						"originY": 4.495145631067961,
						"originalSource": "",
						"exportFormat": "lossless",
						"exportQuality": 0.8,
						"fileType": "image/png",
						"imageSpriteId": 8496575,
						"useCollisionPoly": true,
						"duration": 1,
						"tag": ""
					},
					{
						"width": 14,
						"height": 16,
						"originX": 53,
						"originY": 29.8125,
						"originalSource": "",
						"exportFormat": "lossless",
						"exportQuality": 0.8,
						"fileType": "image/png",
						"imageSpriteId": 3516334,
						"useCollisionPoly": true,
						"duration": 1,
						"tag": ""
					},
					{
						"width": 1920,
						"height": 1080,
						"originX": 0.46875,
						"originY": 0.5055555555555555,
						"originalSource": "",
						"exportFormat": "lossless",
						"exportQuality": 0.8,
						"fileType": "image/png",
						"imageSpriteId": 9357497,
						"useCollisionPoly": true,
						"duration": 1,
						"tag": ""
					}
				],
				"sid": 695413042182556,
				"name": "pagurus",
				"isLooping": false,
				"isPingPong": false,
				"repeatCount": 1,
				"repeatTo": 0,
				"speed": 20
			}
		],
		"subfolders": []
	}
}