{
	"name": "bushShad",
	"plugin-id": "Sprite",
	"sid": 804792896590930,
	"isGlobal": false,
	"editorNewInstanceIsReplica": true,
	"instanceVariables": [],
	"behaviorTypes": [
		{
			"behaviorId": "NoSave",
			"name": "NoSave",
			"sid": 670895603858125
		}
	],
	"effectTypes": [],
	"animations": {
		"items": [
			{
				"frames": [
					{
						"width": 157,
						"height": 63,
						"originX": 0.5095541401273885,
						"originY": 0.4444444444444444,
						"originalSource": "",
						"exportFormat": "lossless",
						"exportQuality": 0.8,
						"fileType": "image/png",
						"imageSpriteId": 143736,
						"collisionPoly": {
							"points": [
								0,
								0.4848483692515979,
								0.22295819213058762,
								0.0606060606060606,
								0.7660043476433152,
								0.055555517023260156,
								1,
								0.5101009137702712,
								0.7251654365994282,
								0.9090909379901307,
								0.21854294530603272,
								0.893939393939394
							]
						},
						"useCollisionPoly": true,
						"duration": 1,
						"tag": ""
					},
					{
						"width": 157,
						"height": 63,
						"originX": 0.49044585987261147,
						"originY": 0.4444444444444444,
						"originalSource": "",
						"exportFormat": "lossless",
						"exportQuality": 0.8,
						"fileType": "image/png",
						"imageSpriteId": 4527011,
						"collisionPoly": {
							"points": [
								0.7814570546939673,
								0.893939393939394,
								0.2748345634005718,
								0.9090909379901307,
								0,
								0.5101009137702712,
								0.23399565235668485,
								0.055555517023260156,
								0.7770418078694123,
								0.0606060606060606,
								1,
								0.4848483692515979
							]
						},
						"useCollisionPoly": true,
						"duration": 1,
						"tag": ""
					},
					{
						"width": 157,
						"height": 63,
						"originX": 0.5159235668789809,
						"originY": 0.49206349206349204,
						"originalSource": "",
						"exportFormat": "lossless",
						"exportQuality": 0.8,
						"fileType": "image/png",
						"imageSpriteId": 2378511,
						"collisionPoly": {
							"points": [
								0,
								0.4848483692515979,
								0.22295819213058762,
								0.0606060606060606,
								0.7660043476433152,
								0.055555517023260156,
								1,
								0.5101009137702712,
								0.7251654365994282,
								0.9090909379901307,
								0.21854294530603272,
								0.893939393939394
							]
						},
						"useCollisionPoly": true,
						"duration": 1,
						"tag": ""
					},
					{
						"width": 157,
						"height": 63,
						"originX": 0.4840764331210191,
						"originY": 0.49206349206349204,
						"originalSource": "",
						"exportFormat": "lossless",
						"exportQuality": 0.8,
						"fileType": "image/png",
						"imageSpriteId": 2107060,
						"collisionPoly": {
							"points": [
								0.7814570546939673,
								0.893939393939394,
								0.2748345634005718,
								0.9090909379901307,
								0,
								0.5101009137702712,
								0.23399565235668485,
								0.055555517023260156,
								0.7770418078694123,
								0.0606060606060606,
								1,
								0.4848483692515979
							]
						},
						"useCollisionPoly": true,
						"duration": 1,
						"tag": ""
					},
					{
						"width": 151,
						"height": 66,
						"originX": 0.5099337748344371,
						"originY": 0.4696969696969697,
						"originalSource": "",
						"exportFormat": "lossless",
						"exportQuality": 0.8,
						"fileType": "image/png",
						"imageSpriteId": 1014238,
						"collisionPoly": {
							"points": [
								0,
								0.4848483692515979,
								0.22295819213058762,
								0.0606060606060606,
								0.7660043476433152,
								0.055555517023260156,
								1,
								0.5101009137702712,
								0.7251654365994282,
								0.9090909379901307,
								0.21854294530603272,
								0.893939393939394
							]
						},
						"useCollisionPoly": true,
						"duration": 1,
						"tag": ""
					},
					{
						"width": 150,
						"height": 75,
						"originX": 0.4966887417218543,
						"originY": 0.5151515151515151,
						"originalSource": "",
						"exportFormat": "lossless",
						"exportQuality": 0.8,
						"fileType": "image/png",
						"imageSpriteId": 9859646,
						"collisionPoly": {
							"points": [
								0.7814570546939673,
								0.893939393939394,
								0.2748345634005718,
								0.9090909379901307,
								0,
								0.5101009137702712,
								0.23399565235668485,
								0.055555517023260156,
								0.7770418078694123,
								0.0606060606060606,
								1,
								0.4848483692515979
							]
						},
						"useCollisionPoly": true,
						"duration": 1,
						"tag": ""
					},
					{
						"width": 72,
						"height": 62,
						"originX": 0.6388888888888888,
						"originY": 0.5161290322580645,
						"originalSource": "",
						"exportFormat": "lossless",
						"exportQuality": 0.8,
						"fileType": "image/png",
						"imageSpriteId": 3732664,
						"collisionPoly": {
							"points": [
								0.4765450335145436,
								0.10777126099706735,
								0.9861111111111112,
								0.09237533720357682,
								0.9861111111111112,
								0.49780068439472447,
								0.9861111111111112,
								0.9596774585086227,
								0.4861727245069758,
								0.9545454545454546,
								0,
								0.5234605280185376
							]
						},
						"useCollisionPoly": true,
						"duration": 1,
						"tag": ""
					},
					{
						"width": 33,
						"height": 33,
						"originX": 0.5,
						"originY": 0.5,
						"originalSource": "",
						"exportFormat": "lossless",
						"exportQuality": 0.8,
						"fileType": "image/png",
						"imageSpriteId": 9376284,
						"collisionPoly": {
							"points": [
								0.3181818181818182,
								0.3181818181818182,
								0.6818181818181818,
								0.3181818181818182,
								0.6818181818181818,
								0.6818181818181818,
								0.3181818181818182,
								0.6818181818181818
							]
						},
						"useCollisionPoly": true,
						"duration": 1,
						"tag": ""
					},
					{
						"width": 33,
						"height": 33,
						"originX": 0.5,
						"originY": 0.5,
						"originalSource": "",
						"exportFormat": "lossless",
						"exportQuality": 0.8,
						"fileType": "image/png",
						"imageSpriteId": 8431749,
						"collisionPoly": {
							"points": [
								0.3181818181818182,
								0.3181818181818182,
								0.6818181818181818,
								0.3181818181818182,
								0.6818181818181818,
								0.6818181818181818,
								0.3181818181818182,
								0.6818181818181818
							]
						},
						"useCollisionPoly": true,
						"duration": 1,
						"tag": ""
					},
					{
						"width": 845,
						"height": 564,
						"originX": 0.5,
						"originY": 0.5,
						"originalSource": "",
						"exportFormat": "lossless",
						"exportQuality": 0.8,
						"fileType": "image/png",
						"imageSpriteId": 3014438,
						"collisionPoly": {
							"points": [
								0,
								1,
								0,
								0,
								1,
								0,
								1,
								1
							]
						},
						"useCollisionPoly": true,
						"duration": 1,
						"tag": ""
					},
					{
						"width": 720,
						"height": 540,
						"originX": 0.5,
						"originY": 0.5,
						"originalSource": "",
						"exportFormat": "lossless",
						"exportQuality": 0.8,
						"fileType": "image/png",
						"imageSpriteId": 1732419,
						"collisionPoly": {
							"points": [
								0,
								1,
								0,
								0,
								1,
								0,
								1,
								1
							]
						},
						"useCollisionPoly": true,
						"duration": 1,
						"tag": ""
					}
				],
				"sid": 473198075900234,
				"name": "shad",
				"isLooping": false,
				"isPingPong": false,
				"repeatCount": 1,
				"repeatTo": 0,
				"speed": 0
			}
		],
		"subfolders": []
	}
}